[
  {
    "category": "绿色出行",
    "categoryDesc": "品牌视觉系统",
    "span": "2x2",
    "works": [
      {
        "title": "九号单车品牌系统",
        "image": "static/images/green/001-branding.jpg"
      }
    ]
  },
  {
    "category": "教育培训",
    "categoryDesc": "品牌与课件体系",
    "works": [
      {
        "title": "知行学堂品牌设计",
        "image": "static/images/edu/001-branding.jpg"
      },
      {
        "title": "招生海报系列",
        "image": "static/images/edu/003-poster.jpg"
      }
    ]
  },
  {
    "category": "电商",
    "categoryDesc": "店铺与营销视觉",
    "works": [
      {
        "title": "甄选好物店铺设计",
        "image": "static/images/ecommerce/001-shop.jpg"
      }
    ]
  },
  {
    "category": "政企",
    "categoryDesc": "UI 与数据可视化",
    "works": [
      {
        "title": "数字政务平台UI",
        "image": "static/images/gov/001-ui.jpg"
      }
    ]
  },
  {
    "category": "独立开发者",
    "categoryDesc": "产品与落地页设计",
    "works": [
      {
        "title": "API 文档设计",
        "image": "static/images/dev/002-docs.jpg"
      },
      {
        "title": "开发者社区视觉",
        "image": "static/images/dev/003-community.jpg"
      }
    ]
  },
  {
    "category": "育儿",
    "categoryDesc": "品牌与内容视觉",
    "works": [
      {
        "title": "育儿研究所品牌",
        "image": "static/images/kids/001-brand.jpg"
      },
      {
        "title": "亲子活动海报",
        "image": "static/images/kids/003-poster.jpg"
      }
    ]
  },
  {
    "category": "体育运动",
    "categoryDesc": "赛事视觉设计",
    "works": [
      {
        "title": "运动品牌视觉",
        "image": "static/images/sports/003-brand.jpg"
      }
    ]
  },
  {
    "category": "旅游",
    "categoryDesc": "目的地视觉与宣传设计",
    "works": [
      {
        "title": "旅游品牌视觉",
        "image": "static/images/travel/001-brand.jpg"
      }
    ]
  },
  {
    "category": "书刊",
    "categoryDesc": "排版与出版物设计",
    "works": [
      {
        "title": "书刊排版设计",
        "image": "static/images/book/001-layout.jpg"
      }
    ]
  }
]